automar/__init__.py
automar/cli/__init__.py
automar/cli/main.py
automar/core/__init__.py
automar/core/__main__.py
automar/core/config.py
automar/core/utils.py
automar/core/models/__init__.py
automar/core/models/crossval.py
automar/core/models/evaluation.py
automar/core/models/feature_importance.py
automar/core/models/forecast.py
automar/core/models/nn.py
automar/core/models/train.py
automar/core/models/tuning.py
automar/core/preprocessing/__init__.py
automar/core/preprocessing/extractor.py
automar/core/preprocessing/loaders.py
automar/core/preprocessing/stats.py
automar/core/preprocessing/tensor.py
automar/core/visuals/__init__.py
automar/core/visuals/auxiliary.py
automar/shared/__init__.py
automar/shared/config/__init__.py
automar/shared/config/config_utils.py
automar/shared/config/path_resolver.py
automar/shared/config/schemas.py
automar/shared/config/templates/config_template.toml
automar/shared/config/templates/hpt_defaults/gru.py
automar/shared/config/templates/hpt_defaults/logreg.py
automar/shared/config/templates/hpt_defaults/transformer.py
automar/shared/core/__init__.py
automar/shared/core/common.py
automar/shared/persistence/__init__.py
automar/shared/persistence/database.py
automar/shared/persistence/job_store.py
automar/shared/persistence/library.py
automar/shared/persistence/schema.py
automar/shared/runners/__init__.py
automar/shared/runners/api_runner.py
automar/shared/runners/crossval_runner.py
automar/shared/runners/extract_runner.py
automar/shared/runners/gui_runner.py
automar/shared/runners/pca_runner.py
automar/shared/runners/predict_runner.py
automar/shared/runners/train_runner.py
automar/shared/runners/tune_runner.py
automar/shared/services/__init__.py
automar/shared/services/crossvalidation_service.py
automar/shared/services/data_acquisition.py
automar/shared/services/device_utils.py
automar/shared/services/extraction_service.py
automar/shared/services/file_utils.py
automar/shared/services/gap_analyzer.py
automar-25.12.12.dist-info/licenses/LICENSE
automar-25.12.12.dist-info/METADATA
automar-25.12.12.dist-info/WHEEL
automar-25.12.12.dist-info/entry_points.txt
automar-25.12.12.dist-info/top_level.txt
automar-25.12.12.dist-info/RECORD
