Metadata-Version: 2.4
Name: automar
Version: 25.12.12
Summary: Time series-based machine learning framework for stock market forecasting
Author-email: "Alejandro Gil (Kzurro)" <patomail@duck.com>, Sergio Pablo-García <spgarcica@gmail.com>
Maintainer: Alejandro Gil (Kzurro)
License-Expression: MIT
Project-URL: homepage, https://codeberg.org/Kzurro/Automar
Project-URL: repository, https://codeberg.org/Kzurro/Automar
Project-URL: documentation, https://codeberg.org/Kzurro/Automar
Project-URL: Bug Tracker, https://codeberg.org/Kzurro/Automar/issues
Keywords: stock,deep learning,machine learning,time series,forecasting,GRU,transformer,financial prediction
Classifier: Development Status :: 4 - Beta
Classifier: Intended Audience :: Financial and Insurance Industry
Classifier: Intended Audience :: Science/Research
Classifier: Programming Language :: Python :: 3
Classifier: Programming Language :: Python :: 3.11
Classifier: Programming Language :: Python :: 3.12
Classifier: Topic :: Scientific/Engineering :: Artificial Intelligence
Classifier: Topic :: Office/Business :: Financial :: Investment
Requires-Python: >=3.12
License-File: LICENSE
Requires-Dist: fastapi
Requires-Dist: joblib
Requires-Dist: lxml
Requires-Dist: numba
Requires-Dist: numpy
Requires-Dist: optuna
Requires-Dist: pandas
Requires-Dist: pandas_market_calendars
Requires-Dist: pyarrow
Requires-Dist: pydantic>=2.8
Requires-Dist: python-multipart
Requires-Dist: requests
Requires-Dist: scikit-learn
Requires-Dist: scipy
Requires-Dist: sktime
Requires-Dist: tomli
Requires-Dist: tomli_w
Requires-Dist: tqdm
Requires-Dist: uvicorn
Requires-Dist: yfinance
Provides-Extra: torch
Requires-Dist: torch>=2.4.0; extra == "torch"
Requires-Dist: torcheval; extra == "torch"
Provides-Extra: ray
Requires-Dist: ray[data,serve,train,tune]>=2.34.0; extra == "ray"
Provides-Extra: all
Requires-Dist: torch>=2.4.0; extra == "all"
Requires-Dist: torcheval; extra == "all"
Requires-Dist: ray[data,serve,train,tune]>=2.34.0; extra == "all"
Dynamic: license-file
